{
  "_meta": {
    "category": "backgrounds",
    "version": "1.0",
    "notes": "Simple background colors, gradients, and abstract backdrop themes. Designed for studio shots, minimal scenes, and controlled environments. Avoids location-based places."
  },

  "white": {
    "tags": [
      "white background",
      "pure white backdrop",
      "clean white studio background"
    ]
  },

  "black": {
    "tags": [
      "black background",
      "dark studio backdrop",
      "deep black background"
    ]
  },

  "gray": {
    "tags": [
      "gray background",
      "neutral gray studio backdrop",
      "soft gray gradient background"
    ]
  },

  "dark": {
    "tags": [
      "dark background",
      "shadowy backdrop",
      "low light background"
    ]
  },

  "light": {
    "tags": [
      "bright background",
      "soft light backdrop",
      "high key background"
    ]
  },

  "sky_blue": {
    "tags": [
      "sky blue background",
      "soft blue backdrop",
      "clear sky colored background"
    ]
  },

  "sunset_gradient": {
    "tags": [
      "sunset gradient background",
      "orange pink gradient backdrop",
      "warm sky gradient"
    ]
  },

  "purple_gradient": {
    "tags": [
      "purple gradient background",
      "violet gradient backdrop",
      "purple fading background"
    ]
  },

  "pastel_gradient": {
    "tags": [
      "pastel gradient background",
      "soft pastel color backdrop",
      "dreamy pastel gradient"
    ]
  },

  "rainbow_gradient": {
    "tags": [
      "rainbow gradient background",
      "multi color gradient backdrop",
      "colorful spectrum background"
    ]
  },

  "studio_seamless": {
    "tags": [
      "seamless studio background",
      "studio paper backdrop",
      "photography studio backdrop"
    ]
  },

  "vignette": {
    "tags": [
      "vignette background",
      "dark edges fading to center",
      "soft vignette backdrop"
    ]
  },

  "bokeh": {
    "tags": [
      "bokeh background",
      "blurred light circles",
      "soft out of focus lights"
    ]
  },

  "sparkle": {
    "tags": [
      "sparkling background",
      "glitter light background",
      "twinkling light particles"
    ]
  },

  "glow": {
    "tags": [
      "soft glowing background",
      "ambient glow backdrop",
      "subtle luminous background"
    ]
  },

  "neon_glow": {
    "tags": [
      "neon glow background",
      "vibrant neon lights",
      "colorful glowing backdrop"
    ]
  },

  "cinematic_dark": {
    "tags": [
      "cinematic dark background",
      "dramatic shadow backdrop",
      "film style dark atmosphere"
    ]
  },

  "foggy": {
    "tags": [
      "foggy background",
      "soft mist backdrop",
      "hazy atmospheric background"
    ]
  },

  "smoke": {
    "tags": [
      "smoky background",
      "smoke swirling in background",
      "dramatic smoke atmosphere"
    ]
  },

  "abstract_light": {
    "tags": [
      "abstract light background",
      "soft glowing shapes",
      "modern abstract lighting"
    ]
  },

  "color_wash": {
    "tags": [
      "color washed background",
      "soft color overlay backdrop",
      "diffused color lighting"
    ]
  },

  "textured_wall": {
    "tags": [
      "textured wall background",
      "subtle textured backdrop",
      "studio texture background"
    ]
  },

  "paint_texture": {
    "tags": [
      "paint texture background",
      "artistic painted backdrop",
      "brush stroke background"
    ]
  }
}